{
  "text": "",
  "quiz": [
    {
      "question": "trustworthy ______",
      "type": "blank",
      "answer": "friend",
      "explanation": "值得信赖的,值得信赖的朋友。She proved to be a trustworthy friend who never revealed secrets.她证明是一个值得信赖的朋友,从不泄露秘密。"
    },
    {
      "question": "_____ leaky",
      "type": "blank",
      "answer": "roof",
      "explanation": "漏水的,漏水的屋顶。The leaky roof caused water damage to the ceiling during the storm.漏水的屋顶在暴风雨期间对天花板造成了水损。"
    },
    {
      "question": "_____ peaky",
      "type": "blank",
      "answer": "look",
      "explanation": "面色苍白的,面色苍白的样子。You have a peaky look today; perhaps you should go home and rest.你今天面色苍白,也许你应该回家休息。"
    },
    {
      "question": "squeaky _____",
      "type": "blank",
      "answer": "shoes",
      "explanation": "吱吱作响的,吱吱作响的鞋子。His new squeaky shoes embarrassed him in the quiet library.他的新吱吱作响的鞋子在安静的图书馆里让他尴尬。"
    },
    {
      "question": "______ croaky",
      "type": "blank",
      "answer": "voice",
      "explanation": "嘶哑的,嘶哑的声音。She had a croaky voice after cheering at the concert all night.在音乐会上欢呼了一整晚后,她的声音嘶哑了。"
    },
    {
      "question": "_____ dicky",
      "type": "blank",
      "answer": "tummy",
      "explanation": "不舒服的,不舒服的肚子。The spoiled food gave him a dicky tummy for the rest of the day.变质的食物让他一整天肚子都不舒服。"
    },
    {
      "question": "panicky ________",
      "type": "blank",
      "answer": "reaction",
      "explanation": "恐慌的,恐慌的反应。Her panicky reaction to the spider made everyone laugh.她对蜘蛛的恐慌反应让每个人都笑了。"
    },
    {
      "question": "______ stocky",
      "type": "blank",
      "answer": "build",
      "explanation": "结实的,结实的体格。The wrestler had a stocky build with broad shoulders and strong arms.摔跤手有结实的体格,肩膀宽阔,手臂强壮。"
    },
    {
      "question": "______ cheeky",
      "type": "blank",
      "answer": "grin",
      "explanation": "厚颜无耻的,厚颜无耻的笑容。The boy flashed a cheeky grin after his mischievous prank.男孩在恶作剧后露出厚颜无耻的笑容。"
    },
    {
      "question": "_____ spiky",
      "type": "blank",
      "answer": "hair",
      "explanation": "尖刺状的,尖刺状的头发。The teenager styled his spiky hair with lots of gel.青少年用大量发胶定型他的尖刺状头发。"
    },
    {
      "question": "_____ bulky",
      "type": "blank",
      "answer": "package",
      "explanation": "笨重的,笨重的包裹。The bulky package was difficult to carry up the stairs.笨重的包裹很难搬上楼梯。"
    },
    {
      "question": "_____ sulky",
      "type": "blank",
      "answer": "silence",
      "explanation": "生闷气的,生闷气的沉默。After the argument, she sat in sulky silence for the rest of the evening.争吵后,她在生闷气的沉默中坐了一整晚。"
    },
    {
      "question": "_____ hanky",
      "type": "blank",
      "answer": "panky",
      "explanation": "手帕,可疑行为。The auditor suspected there was some hanky panky with the company's finances.审计员怀疑公司财务存在一些可疑行为。"
    },
    {
      "question": "_____ lanky",
      "type": "blank",
      "answer": "teen",
      "explanation": "瘦长的,瘦长的少年。The lanky teen had outgrown all his clothes over the summer.这个瘦长的少年在夏天长得穿不下所有衣服了。"
    },
    {
      "question": "_____ manky",
      "type": "blank",
      "answer": "towel",
      "explanation": "脏的,脏毛巾。The gym's manky towel smelled musty and needed to be washed.健身房的脏毛巾有霉味,需要清洗。"
    },
    {
      "question": "______ cranky",
      "type": "blank",
      "answer": "toddler",
      "explanation": "脾气暴躁的,脾气暴躁的幼儿。The cranky toddler needed a nap after missing his afternoon rest.脾气暴躁的幼儿错过了下午休息后需要小睡。"
    },
    {
      "question": "______ spooky",
      "type": "blank",
      "answer": "story",
      "explanation": "恐怖的,恐怖的故事。The children huddled together listening to the spooky story.孩子们挤在一起听恐怖的故事。"
    },
    {
      "question": "_____ murky",
      "type": "blank",
      "answer": "water",
      "explanation": "浑浊的,浑浊的水。The murky water in the pond made it impossible to see the bottom.池塘里浑浊的水使人无法看到底部。"
    },
    {
      "question": "_____ dusky",
      "type": "blank",
      "answer": "sky",
      "explanation": "昏暗的,昏暗的天空。The dusky sky at twilight painted the horizon in shades of purple.黄昏时昏暗的天空将地平线染成紫色。"
    },
    {
      "question": "_____ scaly",
      "type": "blank",
      "answer": "skin",
      "explanation": "有鳞的,有鳞的皮肤。The reptile's scaly skin protected it from the harsh environment.爬行动物有鳞的皮肤保护它免受恶劣环境的影响。"
    },
    {
      "question": "____ dependably",
      "type": "blank",
      "answer": "work",
      "explanation": "可靠地,可靠地工作。She always manages to work dependably even under pressure.即使在压力下,她也总是能够可靠地工作。"
    },
    {
      "question": "invariably ____",
      "type": "blank",
      "answer": "true",
      "explanation": "总是,总是正确。His predictions about the weather were invariably true.他对天气的预测总是正确的。"
    },
    {
      "question": "admirably _______",
      "type": "blank",
      "answer": "handled",
      "explanation": "令人钦佩地,令人钦佩地处理。The crisis was admirably handled by the experienced team.危机被经验丰富的团队令人钦佩地处理了。"
    },
    {
      "question": "unaccountably ______",
      "type": "blank",
      "answer": "absent",
      "explanation": "莫名其妙地,莫名其妙地缺席。The key witness was unaccountably absent from the trial.关键证人莫名其妙地在审判中缺席。"
    },
    {
      "question": "_______ knobbly",
      "type": "blank",
      "answer": "knees",
      "explanation": "多节的,多节的膝盖。The elderly woman's knobbly knees showed signs of arthritis.老妇人多节的膝盖显示出关节炎的迹象。"
    },
    {
      "question": "bubbly ___________",
      "type": "blank",
      "answer": "personality",
      "explanation": "活泼的,活泼的性格。Her bubbly personality made her popular at every social gathering.她活泼的性格使她在每次社交聚会上都很受欢迎。"
    },
    {
      "question": "_______ stubbly",
      "type": "blank",
      "answer": "beard",
      "explanation": "胡茬的,胡茬的胡须。His stubbly beard needed shaving after several days of travel.经过几天旅行后,他胡茬的胡须需要刮了。"
    },
    {
      "question": "audibly ____",
      "type": "blank",
      "answer": "gasp",
      "explanation": "可听见地,可听见地倒吸气。The audience began to audibly gasp at the magician's stunning trick.观众开始可听见地倒吸气,惊叹于魔术师惊人的戏法。"
    },
    {
      "question": "____ nimbly",
      "type": "blank",
      "answer": "move",
      "explanation": "敏捷地,敏捷地移动。The gymnast could move nimbly across the balance beam.体操运动员能够敏捷地在平衡木上移动。"
    },
    {
      "question": "______ numbly",
      "type": "blank",
      "answer": "answer",
      "explanation": "麻木地,麻木地回答。She could only answer numbly after hearing the shocking news.听到震惊的消息后,她只能麻木地回答。"
    },
    {
      "question": "_______ superbly",
      "type": "blank",
      "answer": "perform",
      "explanation": "极好地,极好地表演。The orchestra managed to perform superbly despite the difficult piece.尽管曲目很难,管弦乐队还是设法极好地表演了。"
    },
    {
      "question": "______ cuddly",
      "type": "blank",
      "answer": "toy",
      "explanation": "可爱的,可爱的玩具。The child hugged the soft cuddly toy tightly before bedtime.孩子在睡前紧紧拥抱柔软可爱的玩具。"
    },
    {
      "question": "lopsidedly _____",
      "type": "blank",
      "answer": "built",
      "explanation": "不对称地,不对称地建造。The old shed was lopsidedly built and leaned to one side.旧棚子不对称地建造,向一边倾斜。"
    },
    {
      "question": "____ doggedly",
      "type": "blank",
      "answer": "work",
      "explanation": "顽强地,顽强地工作。He continued to work doggedly despite numerous setbacks.尽管遇到无数挫折,他仍继续顽强地工作。"
    },
    {
      "question": "_____ crookedly",
      "type": "blank",
      "answer": "smile",
      "explanation": "歪斜地,歪斜地微笑。The villain would smile crookedly before revealing his evil plan.恶棍在揭示他的邪恶计划之前会歪斜地微笑。"
    },
    {
      "question": "___ resignedly",
      "type": "blank",
      "answer": "nod",
      "explanation": "顺从地,顺从地点头。She could only nod resignedly when told she had to work overtime.当被告知必须加班时,她只能顺从地点头。"
    },
    {
      "question": "_____ unrestrainedly",
      "type": "blank",
      "answer": "laugh",
      "explanation": "无拘束地,无拘束地大笑。The children began to laugh unrestrainedly at the clown's antics.孩子们开始无拘束地大笑看小丑的滑稽动作。"
    },
    {
      "question": "____ unconcernedly",
      "type": "blank",
      "answer": "look",
      "explanation": "漠不关心地,漠不关心地看。He continued to look unconcernedly at his phone during the meeting.在会议期间,他继续漠不关心地看他的手机。"
    },
    {
      "question": "___ composedly",
      "type": "blank",
      "answer": "sit",
      "explanation": "镇定地,镇定地坐。She managed to sit composedly despite her racing heart.尽管心跳加速,她还是设法镇定地坐着。"
    },
    {
      "question": "_____ heatedly",
      "type": "blank",
      "answer": "argue",
      "explanation": "激烈地,激烈地争论。The politicians began to argue heatedly over the controversial policy.政治家们开始就有争议的政策激烈地争论。"
    },
    {
      "question": "____ dejectedly",
      "type": "blank",
      "answer": "sigh",
      "explanation": "沮丧地,沮丧地叹气。He could only sigh dejectedly after losing the championship game.输掉冠军赛后,他只能沮丧地叹气。"
    },
    {
      "question": "____ spiritedly",
      "type": "blank",
      "answer": "play",
      "explanation": "精神饱满地,精神饱满地玩。The team continued to play spiritedly despite being behind in score.尽管比分落后,球队仍继续精神饱满地比赛。"
    },
    {
      "question": "____ dispiritedly",
      "type": "blank",
      "answer": "walk",
      "explanation": "沮丧地,沮丧地走。After the rejection, she began to walk dispiritedly home.遭到拒绝后,她开始沮丧地走回家。"
    },
    {
      "question": "___ contentedly",
      "type": "blank",
      "answer": "eat",
      "explanation": "满足地,满足地吃。The cat would eat contentedly while purring loudly.猫会满足地吃着,同时大声打呼噜。"
    },
    {
      "question": "___ pointedly",
      "type": "blank",
      "answer": "say",
      "explanation": "尖刻地,尖刻地说。She would say pointedly that punctuality was important.她会尖刻地说守时很重要。"
    },
    {
      "question": "admittedly ____",
      "type": "blank",
      "answer": "true",
      "explanation": "诚然,诚然正确。The statement was admittedly true but still quite hurtful.这个说法诚然正确,但仍然相当伤人。"
    },
    {
      "question": "____ perplexedly",
      "type": "blank",
      "answer": "look",
      "explanation": "困惑地,困惑地看。He began to look perplexedly at the complex mathematical equation.他开始困惑地看着复杂的数学方程式。"
    },
    {
      "question": "_____ fixedly",
      "type": "blank",
      "answer": "stare",
      "explanation": "专注地,专注地凝视。She would stare fixedly at the painting trying to understand its meaning.她专注地凝视着这幅画,试图理解它的含义。"
    },
    {
      "question": "_____ dazedly",
      "type": "blank",
      "answer": "reply",
      "explanation": "茫然地,茫然地回答。The accident victim could only reply dazedly to the paramedic's questions.事故受害者只能茫然地回答医护人员的问题。"
    },
    {
      "question": "___ idly",
      "type": "blank",
      "answer": "sit",
      "explanation": "无所事事地,无所事事地坐。He would sit idly watching television instead of doing homework.他会无所事事地坐着看电视而不是做作业。"
    },
    {
      "question": "_____ rigidly",
      "type": "blank",
      "answer": "stand",
      "explanation": "僵硬地,僵硬地站立。The soldiers continued to stand rigidly at attention during inspection.士兵们在检阅期间继续僵硬地立正站立。"
    },
    {
      "question": "_____ timidly",
      "type": "blank",
      "answer": "speak",
      "explanation": "胆怯地,胆怯地说话。The shy child began to speak timidly when asked a question.当被问到问题时,害羞的孩子开始胆怯地说话。"
    },
    {
      "question": "____ languidly",
      "type": "blank",
      "answer": "move",
      "explanation": "懒洋洋地,懒洋洋地移动。The cat would move languidly across the sunny windowsill.猫会懒洋洋地在阳光明媚的窗台上移动。"
    },
    {
      "question": "____ avidly",
      "type": "blank",
      "answer": "read",
      "explanation": "贪婪地,贪婪地阅读。The book lover would read avidly for hours every evening.书迷每天晚上会贪婪地阅读几个小时。"
    },
    {
      "question": "_____ baldly",
      "type": "blank",
      "answer": "state",
      "explanation": "直截了当地,直截了当地陈述。He would state baldly that the project had failed completely.他会直截了当地陈述项目已经完全失败。"
    },
    {
      "question": "_____ blandly",
      "type": "blank",
      "answer": "smile",
      "explanation": "平淡地,平淡地微笑。She continued to smile blandly despite the awkward situation.尽管情况尴尬,她仍继续平淡地微笑。"
    },
    {
      "question": "___ unfriendly",
      "type": "blank",
      "answer": "act",
      "explanation": "不友好地,不友好地行动。The neighbors began to act unfriendly after the property dispute.财产纠纷后,邻居们开始不友好地行动。"
    },
    {
      "question": "_______ spindly",
      "type": "blank",
      "answer": "legs",
      "explanation": "细长的,细长的腿。The newborn foal stood on spindly legs that wobbled unsteadily.新生的小马驹站在颤抖不稳的细长腿上。"
    },
    {
      "question": "_____ soundly",
      "type": "blank",
      "answer": "sleep",
      "explanation": "酣睡地,酣睡。The exhausted hiker would sleep soundly through the night.精疲力竭的徒步旅行者会整夜酣睡。"
    },
    {
      "question": "_____ inwardly",
      "type": "blank",
      "answer": "think",
      "explanation": "内心地,内心地思考。She would think inwardly that the plan was doomed to fail.她会内心地认为这个计划注定要失败。"
    },
    {
      "question": "____ haphazardly",
      "type": "blank",
      "answer": "work",
      "explanation": "杂乱无章地,杂乱无章地工作。He tends to work haphazardly without proper planning or organization.他倾向于杂乱无章地工作,没有适当的计划或组织。"
    },
    {
      "question": "scarcely ___",
      "type": "blank",
      "answer": "any",
      "explanation": "几乎不,几乎没有。There was scarcely any food left after the hungry guests departed.饥饿的客人离开后几乎没有食物剩下。"
    },
    {
      "question": "______ snidely",
      "type": "blank",
      "answer": "remark",
      "explanation": "讽刺地,讽刺地评论。He would remark snidely about others' mistakes to feel superior.他会讽刺地评论别人的错误以感到优越。"
    },
    {
      "question": "_____ steely",
      "type": "blank",
      "answer": "stare",
      "explanation": "冷酷的,冷酷的凝视。The detective gave the suspect a hard steely stare during questioning.侦探在审问期间给了嫌疑人一个冷酷的凝视。"
    },
    {
      "question": "______ savagely",
      "type": "blank",
      "answer": "attack",
      "explanation": "野蛮地,野蛮地攻击。The wild animal would attack savagely when defending its territory.野生动物在保卫领地时会野蛮地攻击。"
    },
    {
      "question": "_________ lamely",
      "type": "blank",
      "answer": "apologize",
      "explanation": "无力地,无力地道歉。He could only apologize lamely for missing the important meeting.他只能无力地为错过重要会议道歉。"
    },
    {
      "question": "___ supremely",
      "type": "blank",
      "answer": "win",
      "explanation": "极其地,极其地获胜。The champion managed to win supremely over all competitors.冠军设法极其地战胜了所有竞争对手。"
    },
    {
      "question": "_____ serenely",
      "type": "blank",
      "answer": "smile",
      "explanation": "平静地,平静地微笑。She continued to smile serenely despite the chaos around her.尽管周围一片混乱,她仍继续平静地微笑。"
    },
    {
      "question": "_____ squarely",
      "type": "blank",
      "answer": "stand",
      "explanation": "正面地,正面地站立。He decided to stand squarely and face his accusers directly.他决定正面地站立,直接面对指责他的人。"
    },
    {
      "question": "______ sorely",
      "type": "blank",
      "answer": "suffer",
      "explanation": "严重地,严重地受苦。The community would suffer sorely from the economic downturn.社区会因经济衰退而严重受苦。"
    },
    {
      "question": "_______ tensely",
      "type": "blank",
      "answer": "breathe",
      "explanation": "紧张地,紧张地呼吸。The audience began to breathe tensely during the suspenseful scene.在悬疑场景中,观众开始紧张地呼吸。"
    },
    {
      "question": "_____ hoarsely",
      "type": "blank",
      "answer": "speak",
      "explanation": "嘶哑地,嘶哑地说话。After shouting all day, he could only speak hoarsely in a whisper.喊了一整天后,他只能嘶哑地低声说话。"
    },
    {
      "question": "_____ delicately",
      "type": "blank",
      "answer": "touch",
      "explanation": "精致地,精致地触摸。The artist would touch delicately the wet paint with her brush.艺术家会用画笔精致地触摸湿颜料。"
    },
    {
      "question": "____ sedately",
      "type": "blank",
      "answer": "walk",
      "explanation": "从容地,从容地走。The elderly couple would walk sedately through the park each morning.老年夫妇每天早上会从容地在公园里散步。"
    },
    {
      "question": "____ disconsolately",
      "type": "blank",
      "answer": "weep",
      "explanation": "伤心地,伤心地哭泣。The bereaved widow would weep disconsolately at the funeral.丧偶的寡妇会在葬礼上伤心地哭泣。"
    },
    {
      "question": "___ affectionately",
      "type": "blank",
      "answer": "hug",
      "explanation": "深情地,深情地拥抱。The grandmother would hug affectionately each grandchild who visited.祖母会深情地拥抱每个来访的孙子。"
    },
    {
      "question": "___ mutely",
      "type": "blank",
      "answer": "sit",
      "explanation": "默默地,默默地坐。The shocked witness could only sit mutely unable to describe what happened.震惊的目击者只能默默地坐着,无法描述发生了什么。"
    },
    {
      "question": "_____ grotesquely",
      "type": "blank",
      "answer": "laugh",
      "explanation": "怪异地,怪异地大笑。The villain would laugh grotesquely while revealing his sinister plan.恶棍在揭示他邪恶计划时会怪异地大笑。"
    },
    {
      "question": "______ brusquely",
      "type": "blank",
      "answer": "answer",
      "explanation": "粗暴地,粗暴地回答。The busy doctor would answer brusquely when interrupted during rounds.忙碌的医生在查房时被打断会粗暴地回答。"
    },
    {
      "question": "_____ gravely",
      "type": "blank",
      "answer": "speak",
      "explanation": "严肃地,严肃地说话。The judge began to speak gravely about the seriousness of the crime.法官开始严肃地谈论罪行的严重性。"
    },
    {
      "question": "_____ evasively",
      "type": "blank",
      "answer": "reply",
      "explanation": "含糊其辞地,含糊其辞地回答。The politician would reply evasively to avoid answering directly.政治家会含糊其辞地回答以避免直接回答。"
    },
    {
      "question": "___ compulsively",
      "type": "blank",
      "answer": "buy",
      "explanation": "强迫性地,强迫性地购买。She would buy compulsively whenever feeling stressed or anxious.每当感到压力或焦虑时,她会强迫性地购买。"
    },
    {
      "question": "_____ convulsively",
      "type": "blank",
      "answer": "shake",
      "explanation": "痉挛地,痉挛地颤抖。His body began to shake convulsively from the fever.他的身体因发烧而开始痉挛地颤抖。"
    },
    {
      "question": "____ apprehensively",
      "type": "blank",
      "answer": "wait",
      "explanation": "忧虑地,忧虑地等待。The family would wait apprehensively for news from the hospital.家人会忧虑地等待医院的消息。"
    },
    {
      "question": "______ impassively",
      "type": "blank",
      "answer": "listen",
      "explanation": "冷漠地,冷漠地倾听。The poker player would listen impassively to his opponents' conversation.扑克玩家会冷漠地倾听对手的谈话。"
    },
    {
      "question": "___ interrogatively",
      "type": "blank",
      "answer": "ask",
      "explanation": "疑问地,疑问地询问。The detective would ask interrogatively about every detail of the crime.侦探会疑问地询问犯罪的每个细节。"
    },
    {
      "question": "___ tentatively",
      "type": "blank",
      "answer": "nod",
      "explanation": "试探性地,试探性地点头。She would nod tentatively unsure if she agreed with the proposal.她会试探性地点头,不确定是否同意该提议。"
    },
    {
      "question": "___ instinctively",
      "type": "blank",
      "answer": "act",
      "explanation": "本能地,本能地行动。The mother would act instinctively to protect her children from danger.母亲会本能地行动保护她的孩子免受危险。"
    },
    {
      "question": "___ plaintively",
      "type": "blank",
      "answer": "cry",
      "explanation": "悲伤地,悲伤地哭泣。The abandoned puppy would cry plaintively for its mother.被遗弃的小狗会悲伤地哭泣寻找它的母亲。"
    },
    {
      "question": "______ furtively",
      "type": "blank",
      "answer": "glance",
      "explanation": "偷偷地,偷偷地看。The thief would glance furtively around before stealing the jewelry.小偷在偷珠宝前会偷偷地环顾四周。"
    },
    {
      "question": "_____ stiffly",
      "type": "blank",
      "answer": "stand",
      "explanation": "僵硬地,僵硬地站立。After the long car ride, he could only stand stiffly with aching muscles.长途车程后,他只能僵硬地站着,肌肉酸痛。"
    },
    {
      "question": "___ gruffly",
      "type": "blank",
      "answer": "say",
      "explanation": "粗声粗气地,粗声粗气地说。The grumpy old man would say gruffly to children playing near his yard.脾气暴躁的老人会粗声粗气地对在他院子附近玩耍的孩子们说话。"
    },
    {
      "question": "____ straggly",
      "type": "blank",
      "answer": "hair",
      "explanation": "蓬乱的,蓬乱的头发。The homeless man had long straggly hair that hadn't been washed in weeks.无家可归的男人有长长的蓬乱头发,好几周没洗了。"
    },
    {
      "question": "_______ wriggly",
      "type": "blank",
      "answer": "worm",
      "explanation": "扭动的,扭动的蠕虫。The child poked at the wriggly worm with a stick.孩子用棍子戳扭动的蠕虫。"
    },
    {
      "question": "________ squiggly",
      "type": "blank",
      "answer": "line",
      "explanation": "弯曲的,弯曲的线。The artist drew a squiggly line across the canvas in bold strokes.艺术家用大胆的笔触在画布上画了一条弯曲的线。"
    },
    {
      "question": "______ wiggly",
      "type": "blank",
      "answer": "tooth",
      "explanation": "松动的,松动的牙齿。The child had a wiggly tooth that was ready to fall out.孩子有一颗松动的牙齿,准备要掉了。"
    },
    {
      "question": "______ gangly",
      "type": "blank",
      "answer": "youth",
      "explanation": "瘦长笨拙的,瘦长笨拙的年轻人。The gangly youth stumbled awkwardly over his own feet.瘦长笨拙的年轻人笨拙地被自己的脚绊倒。"
    },
    {
      "question": "_____ convincingly",
      "type": "blank",
      "answer": "argue",
      "explanation": "令人信服地,令人信服地争论。The lawyer managed to argue convincingly in defense of her client.律师设法令人信服地为她的客户辩护。"
    },
    {
      "question": "___ piercingly",
      "type": "blank",
      "answer": "cry",
      "explanation": "刺耳地,刺耳地哭喊。The baby began to cry piercingly in the middle of the night.婴儿在半夜开始刺耳地哭喊。"
    },
    {
      "question": "exceedingly ____",
      "type": "blank",
      "answer": "rare",
      "explanation": "极其,极其罕见。The butterfly species was exceedingly rare with only a few specimens found.这种蝴蝶物种极其罕见,只发现了几个标本。"
    }
  ]
}
